perdir/__init__.py
perdir/main.py
perdir-1.dist-info/METADATA
perdir-1.dist-info/WHEEL
perdir-1.dist-info/entry_points.txt
perdir-1.dist-info/top_level.txt
perdir-1.dist-info/RECORD
