Metadata-Version: 2.1
Name: perdir
Version: 1
Summary: Execute commands per directory easily and concurrently
Home-page: https://github.com/twiebe/perdir
Author: Thomas Wiebe
Author-email: code@heimblick.net
License: BSD
Platform: any
Classifier: Intended Audience :: Developers
Classifier: License :: OSI Approved :: BSD License
Classifier: Operating System :: OS Independent
Classifier: Programming Language :: Python
Classifier: Topic :: Software Development :: Libraries :: Python Modules
Requires-Dist: progressbar2
Requires-Dist: termcolor
